quart_injector/__init__.py
quart_injector/module.py
quart_injector/py.typed
quart_injector/scope.py
quart_injector/wiring.py
quart_injector-0.0.0b1.dist-info/WHEEL
quart_injector-0.0.0b1.dist-info/METADATA
quart_injector-0.0.0b1.dist-info/RECORD
