Metadata-Version: 2.1
Name: quart-injector
Version: 0.0.0b1
Summary: 
Author: Daniel Knell
Author-email: contact@danielknell.co.uk
Requires-Python: >=3.10,<4.0
Classifier: Programming Language :: Python :: 3
Classifier: Programming Language :: Python :: 3.10
Requires-Dist: injector (>=0.19.0,<1.0.0)
Requires-Dist: quart (>=0.17.0,<1.0.0)
